[
  {
    "id": "dds001",
    "question": "Vous êtes témoin d’un accident de la route et une personne est blessée. Vous décidez de partir sans aider. Quel devoir n’est pas respecté ?",
    "type": "situational",
    "topic": "droits_devoirs",
    "choices": [
      { "label": "Le devoir de porter assistance à une personne en danger", "isCorrect": true },
      { "label": "Le devoir de réserve", "isCorrect": false },
      { "label": "Le droit de circuler", "isCorrect": false },
      { "label": "La liberté d’expression", "isCorrect": false }
    ],
    "explanation": "En France, ne pas porter secours à une personne en danger est une infraction.",
    "difficulty": "hard"
  },
  {
    "id": "dds002",
    "question": "Vous n’êtes pas d’accord avec une loi, mais vous continuez à la respecter. Quel principe appliquez-vous ?",
    "type": "situational",
    "topic": "droits_devoirs",
    "choices": [
      { "label": "Le respect de la loi dans un État de droit", "isCorrect": true },
      { "label": "La soumission aveugle", "isCorrect": false },
      { "label": "La neutralité politique", "isCorrect": false },
      { "label": "La liberté d’opinion uniquement", "isCorrect": false }
    ],
    "explanation": "Dans un État de droit, la loi s’impose à tous.",
    "difficulty": "medium"
  },
  {
    "id": "dds003",
    "question": "Vous refusez de payer vos impôts car vous jugez les services publics inefficaces. Est-ce conforme aux devoirs du citoyen ?",
    "type": "situational",
    "topic": "droits_devoirs",
    "choices": [
      { "label": "Non, le paiement des impôts est obligatoire", "isCorrect": true },
      { "label": "Oui, c’est un droit individuel", "isCorrect": false },
      { "label": "Oui, si on proteste", "isCorrect": false },
      { "label": "Oui, pour les citoyens naturalisés", "isCorrect": false }
    ],
    "explanation": "Les impôts financent les services publics et sont obligatoires.",
    "difficulty": "hard"
  },
  {
    "id": "dds004",
    "question": "Vous participez à une manifestation autorisée et pacifique. Quel droit exercez-vous ?",
    "type": "situational",
    "topic": "droits_devoirs",
    "choices": [
      { "label": "Le droit de manifester", "isCorrect": true },
      { "label": "Le droit de grève", "isCorrect": false },
      { "label": "Le devoir de réserve", "isCorrect": false },
      { "label": "Le droit de désobéir", "isCorrect": false }
    ],
    "explanation": "La liberté de manifester est un droit fondamental.",
    "difficulty": "medium"
  },
  {
    "id": "dds005",
    "question": "Vous tenez des propos haineux contre un groupe de personnes sur internet. Quel droit dépasse ses limites ?",
    "type": "situational",
    "topic": "droits_devoirs",
    "choices": [
      { "label": "La liberté d’expression", "isCorrect": true },
      { "label": "La liberté religieuse", "isCorrect": false },
      { "label": "Le droit de vote", "isCorrect": false },
      { "label": "Le droit syndical", "isCorrect": false }
    ],
    "explanation": "La liberté d’expression est limitée par la loi.",
    "difficulty": "hard"
  },

  {
    "id": "dds006",
    "question": "Vous êtes convoqué comme juré d’assises et vous refusez sans motif valable. Quel devoir n’est pas respecté ?",
    "type": "situational",
    "topic": "droits_devoirs",
    "choices": [
      { "label": "Le devoir civique de participer à la justice", "isCorrect": true },
      { "label": "Le droit à la vie privée", "isCorrect": false },
      { "label": "La liberté professionnelle", "isCorrect": false },
      { "label": "Le droit de grève", "isCorrect": false }
    ],
    "explanation": "Être juré est un devoir civique.",
    "difficulty": "hard"
  },
  {
    "id": "dds007",
    "question": "Vous critiquez librement une décision politique sans insulter ni menacer. Quel droit exercez-vous ?",
    "type": "situational",
    "topic": "droits_devoirs",
    "choices": [
      { "label": "La liberté d’expression", "isCorrect": true },
      { "label": "Le droit de désobéir", "isCorrect": false },
      { "label": "Le devoir de réserve", "isCorrect": false },
      { "label": "Le droit syndical", "isCorrect": false }
    ],
    "explanation": "La critique des décisions politiques est autorisée.",
    "difficulty": "medium"
  },
  {
    "id": "dds008",
    "question": "Vous refusez de respecter le règlement intérieur d’un lieu public. Quel devoir est remis en cause ?",
    "type": "situational",
    "topic": "droits_devoirs",
    "choices": [
      { "label": "Le respect des règles communes", "isCorrect": true },
      { "label": "Le droit de propriété", "isCorrect": false },
      { "label": "La liberté religieuse", "isCorrect": false },
      { "label": "Le droit d’asile", "isCorrect": false }
    ],
    "explanation": "Les règles communes garantissent le vivre-ensemble.",
    "difficulty": "medium"
  },
  {
    "id": "dds009",
    "question": "Vous votez lors d’une élection. De quel droit s’agit-il ?",
    "type": "situational",
    "topic": "droits_devoirs",
    "choices": [
      { "label": "Le droit de vote", "isCorrect": true },
      { "label": "Le droit de grève", "isCorrect": false },
      { "label": "Le devoir fiscal", "isCorrect": false },
      { "label": "Le droit syndical", "isCorrect": false }
    ],
    "explanation": "Le droit de vote est un droit civique fondamental.",
    "difficulty": "medium"
  },
  {
    "id": "dds010",
    "question": "Vous ne respectez pas une décision de justice définitive. Quel principe est remis en cause ?",
    "type": "situational",
    "topic": "droits_devoirs",
    "choices": [
      { "label": "Le respect de l’autorité judiciaire", "isCorrect": true },
      { "label": "La liberté individuelle", "isCorrect": false },
      { "label": "La neutralité", "isCorrect": false },
      { "label": "La fraternité", "isCorrect": false }
    ],
    "explanation": "Les décisions de justice doivent être respectées.",
    "difficulty": "hard"
  },

  {
    "id": "dds011",
    "question": "Vous participez à une grève légale pour défendre vos conditions de travail. Quel droit exercez-vous ?",
    "type": "situational",
    "topic": "droits_devoirs",
    "choices": [
      { "label": "Le droit de grève", "isCorrect": true },
      { "label": "La liberté religieuse", "isCorrect": false },
      { "label": "Le droit de vote", "isCorrect": false },
      { "label": "Le devoir fiscal", "isCorrect": false }
    ],
    "explanation": "Le droit de grève permet de défendre des intérêts professionnels.",
    "difficulty": "medium"
  },
  {
    "id": "dds012",
    "question": "Vous refusez toute discrimination dans votre comportement quotidien. Quel devoir respectez-vous ?",
    "type": "situational",
    "topic": "droits_devoirs",
    "choices": [
      { "label": "Le devoir de respecter l’égalité", "isCorrect": true },
      { "label": "Le devoir fiscal", "isCorrect": false },
      { "label": "Le devoir militaire", "isCorrect": false },
      { "label": "Le devoir de réserve", "isCorrect": false }
    ],
    "explanation": "Le respect de l’égalité est une obligation civique.",
    "difficulty": "medium"
  },

  {
    "id": "dds013",
    "question": "Vous empêchez quelqu’un d’exercer son droit de vote. Quel droit violez-vous ?",
    "type": "situational",
    "topic": "droits_devoirs",
    "choices": [
      { "label": "Le droit de vote", "isCorrect": true },
      { "label": "La liberté religieuse", "isCorrect": false },
      { "label": "Le droit de grève", "isCorrect": false },
      { "label": "Le droit syndical", "isCorrect": false }
    ],
    "explanation": "Empêcher de voter est une infraction grave.",
    "difficulty": "hard"
  },
  {
    "id": "dds014",
    "question": "Vous respectez les lois même lorsqu’elles vous contraignent. Quel devoir appliquez-vous ?",
    "type": "situational",
    "topic": "droits_devoirs",
    "choices": [
      { "label": "Le devoir de respecter la loi", "isCorrect": true },
      { "label": "Le devoir de réserve", "isCorrect": false },
      { "label": "Le devoir de neutralité", "isCorrect": false },
      { "label": "Le droit de désobéir", "isCorrect": false }
    ],
    "explanation": "Le respect de la loi est un devoir fondamental.",
    "difficulty": "medium"
  },
  {
    "id": "dds015",
    "question": "Vous aidez une personne en difficulté sans y être obligé. Quel principe respectez-vous ?",
    "type": "situational",
    "topic": "droits_devoirs",
    "choices": [
      { "label": "La fraternité", "isCorrect": true },
      { "label": "La neutralité", "isCorrect": false },
      { "label": "La laïcité", "isCorrect": false },
      { "label": "Le devoir fiscal", "isCorrect": false }
    ],
    "explanation": "La fraternité encourage l’entraide.",
    "difficulty": "medium"
  },

  {
    "id": "dds016",
    "question": "Vous respectez les règles de circulation même sans contrôle. Quel devoir appliquez-vous ?",
    "type": "situational",
    "topic": "droits_devoirs",
    "choices": [
      { "label": "Le respect des règles communes", "isCorrect": true },
      { "label": "La liberté individuelle", "isCorrect": false },
      { "label": "Le droit de propriété", "isCorrect": false },
      { "label": "La liberté d’opinion", "isCorrect": false }
    ],
    "explanation": "Les règles garantissent la sécurité collective.",
    "difficulty": "medium"
  },
  {
    "id": "dds017",
    "question": "Vous refusez de témoigner devant la justice sans raison valable. Quel devoir est concerné ?",
    "type": "situational",
    "topic": "droits_devoirs",
    "choices": [
      { "label": "Le devoir de coopérer avec la justice", "isCorrect": true },
      { "label": "Le droit au silence politique", "isCorrect": false },
      { "label": "Le devoir fiscal", "isCorrect": false },
      { "label": "Le droit syndical", "isCorrect": false }
    ],
    "explanation": "La justice repose sur la participation des citoyens.",
    "difficulty": "hard"
  },
  {
    "id": "dds018",
    "question": "Vous adhérez à un syndicat pour défendre vos intérêts professionnels. Quel droit exercez-vous ?",
    "type": "situational",
    "topic": "droits_devoirs",
    "choices": [
      { "label": "Le droit syndical", "isCorrect": true },
      { "label": "Le droit de grève", "isCorrect": false },
      { "label": "Le devoir fiscal", "isCorrect": false },
      { "label": "Le devoir de réserve", "isCorrect": false }
    ],
    "explanation": "Le droit syndical est garanti par la République.",
    "difficulty": "medium"
  },
  {
    "id": "dds019",
    "question": "Vous respectez les droits d’autrui même quand ils sont différents des vôtres. Quel principe appliquez-vous ?",
    "type": "situational",
    "topic": "droits_devoirs",
    "choices": [
      { "label": "Le respect des libertés d’autrui", "isCorrect": true },
      { "label": "La neutralité", "isCorrect": false },
      { "label": "La soumission", "isCorrect": false },
      { "label": "L’individualisme", "isCorrect": false }
    ],
    "explanation": "Les libertés s’exercent dans le respect d’autrui.",
    "difficulty": "medium"
  },
  {
    "id": "dds020",
    "question": "Vous refusez toute violence dans un débat politique. Quel devoir respectez-vous ?",
    "type": "situational",
    "topic": "droits_devoirs",
    "choices": [
      { "label": "Le respect du débat démocratique", "isCorrect": true },
      { "label": "La neutralité religieuse", "isCorrect": false },
      { "label": "Le devoir fiscal", "isCorrect": false },
      { "label": "Le droit de grève", "isCorrect": false }
    ],
    "explanation": "La démocratie repose sur le dialogue pacifique.",
    "difficulty": "medium"
  },

  {
    "id": "dds021",
    "question": "Vous respectez la vie privée d’autrui. Quel droit protégez-vous ?",
    "type": "situational",
    "topic": "droits_devoirs",
    "choices": [
      { "label": "Le droit au respect de la vie privée", "isCorrect": true },
      { "label": "Le droit de vote", "isCorrect": false },
      { "label": "Le devoir fiscal", "isCorrect": false },
      { "label": "Le droit syndical", "isCorrect": false }
    ],
    "explanation": "La vie privée est protégée par la loi.",
    "difficulty": "medium"
  },
  {
    "id": "dds022",
    "question": "Vous refusez de participer à un acte illégal même sous pression. Quel devoir appliquez-vous ?",
    "type": "situational",
    "topic": "droits_devoirs",
    "choices": [
      { "label": "Le respect de la loi", "isCorrect": true },
      { "label": "La solidarité obligatoire", "isCorrect": false },
      { "label": "La neutralité", "isCorrect": false },
      { "label": "Le droit de grève", "isCorrect": false }
    ],
    "explanation": "La loi s’impose à tous.",
    "difficulty": "medium"
  },
  {
    "id": "dds023",
    "question": "Vous respectez la liberté religieuse d’autrui sans partager ses croyances. Quel droit respectez-vous ?",
    "type": "situational",
    "topic": "droits_devoirs",
    "choices": [
      { "label": "La liberté de conscience", "isCorrect": true },
      { "label": "Le devoir fiscal", "isCorrect": false },
      { "label": "Le droit de vote", "isCorrect": false },
      { "label": "La neutralité politique", "isCorrect": false }
    ],
    "explanation": "La liberté de conscience est un droit fondamental.",
    "difficulty": "medium"
  },
  {
    "id": "dds024",
    "question": "Vous respectez les biens publics comme s’ils étaient les vôtres. Quel devoir appliquez-vous ?",
    "type": "situational",
    "topic": "droits_devoirs",
    "choices": [
      { "label": "Le respect des biens publics", "isCorrect": true },
      { "label": "La neutralité", "isCorrect": false },
      { "label": "Le droit de propriété", "isCorrect": false },
      { "label": "La liberté religieuse", "isCorrect": false }
    ],
    "explanation": "Les biens publics appartiennent à tous.",
    "difficulty": "medium"
  },
  {
    "id": "dds025",
    "question": "Vous participez à la vie associative locale. Quel droit exercez-vous ?",
    "type": "situational",
    "topic": "droits_devoirs",
    "choices": [
      { "label": "La liberté d’association", "isCorrect": true },
      { "label": "Le droit de grève", "isCorrect": false },
      { "label": "Le devoir fiscal", "isCorrect": false },
      { "label": "Le devoir de réserve", "isCorrect": false }
    ],
    "explanation": "La liberté d’association est garantie.",
    "difficulty": "medium"
  },

  {
    "id": "dds026",
    "question": "Vous acceptez les contrôles de police dans le respect de la loi. Quel devoir appliquez-vous ?",
    "type": "situational",
    "topic": "droits_devoirs",
    "choices": [
      { "label": "Le respect de l’autorité publique", "isCorrect": true },
      { "label": "La soumission", "isCorrect": false },
      { "label": "La neutralité religieuse", "isCorrect": false },
      { "label": "Le devoir fiscal", "isCorrect": false }
    ],
    "explanation": "L’autorité publique agit dans le cadre de la loi.",
    "difficulty": "medium"
  },
  {
    "id": "dds027",
    "question": "Vous refusez toute forme de corruption. Quel devoir respectez-vous ?",
    "type": "situational",
    "topic": "droits_devoirs",
    "choices": [
      { "label": "Le respect de la loi et de l’éthique", "isCorrect": true },
      { "label": "La neutralité", "isCorrect": false },
      { "label": "La liberté individuelle", "isCorrect": false },
      { "label": "Le droit syndical", "isCorrect": false }
    ],
    "explanation": "La corruption est interdite par la loi.",
    "difficulty": "hard"
  },
  {
    "id": "dds028",
    "question": "Vous exprimez vos opinions sans empêcher les autres de s’exprimer. Quel droit respectez-vous ?",
    "type": "situational",
    "topic": "droits_devoirs",
    "choices": [
      { "label": "La liberté d’expression de tous", "isCorrect": true },
      { "label": "Le droit de vote", "isCorrect": false },
      { "label": "Le devoir fiscal", "isCorrect": false },
      { "label": "La neutralité", "isCorrect": false }
    ],
    "explanation": "La liberté d’expression est partagée.",
    "difficulty": "medium"
  },
  {
    "id": "dds029",
    "question": "Vous respectez les droits des travailleurs dans votre entreprise. Quel principe appliquez-vous ?",
    "type": "situational",
    "topic": "droits_devoirs",
    "choices": [
      { "label": "Le respect des droits sociaux", "isCorrect": true },
      { "label": "La neutralité", "isCorrect": false },
      { "label": "Le devoir fiscal", "isCorrect": false },
      { "label": "La liberté religieuse", "isCorrect": false }
    ],
    "explanation": "Les droits sociaux font partie des droits fondamentaux.",
    "difficulty": "medium"
  },
  {
    "id": "dds030",
    "question": "Vous respectez les décisions prises démocratiquement même si vous avez voté contre. Quel devoir appliquez-vous ?",
    "type": "situational",
    "topic": "droits_devoirs",
    "choices": [
      { "label": "Le respect du résultat démocratique", "isCorrect": true },
      { "label": "La neutralité politique", "isCorrect": false },
      { "label": "Le droit de désobéir", "isCorrect": false },
      { "label": "La fraternité", "isCorrect": false }
    ],
    "explanation": "La démocratie repose sur l’acceptation du vote.",
    "difficulty": "medium"
  },

  {
    "id": "dds031",
    "question": "Vous refusez de tricher lors d’un examen ou concours. Quel devoir respectez-vous ?",
    "type": "situational",
    "topic": "droits_devoirs",
    "choices": [
      { "label": "Le respect de l’égalité et de l’honnêteté", "isCorrect": true },
      { "label": "La neutralité", "isCorrect": false },
      { "label": "La liberté individuelle", "isCorrect": false },
      { "label": "Le droit syndical", "isCorrect": false }
    ],
    "explanation": "L’égalité implique l’honnêteté.",
    "difficulty": "medium"
  },
  {
    "id": "dds032",
    "question": "Vous respectez l’environnement et les règles écologiques. Quel devoir appliquez-vous ?",
    "type": "situational",
    "topic": "droits_devoirs",
    "choices": [
      { "label": "Le devoir de préserver l’environnement", "isCorrect": true },
      { "label": "La neutralité", "isCorrect": false },
      { "label": "Le droit de propriété", "isCorrect": false },
      { "label": "La liberté religieuse", "isCorrect": false }
    ],
    "explanation": "La protection de l’environnement est un devoir citoyen.",
    "difficulty": "medium"
  },
  {
    "id": "dds033",
    "question": "Vous acceptez que vos droits soient limités pour protéger la sécurité collective. Quel principe respectez-vous ?",
    "type": "situational",
    "topic": "droits_devoirs",
    "choices": [
      { "label": "L’équilibre entre libertés et sécurité", "isCorrect": true },
      { "label": "La soumission", "isCorrect": false },
      { "label": "La neutralité religieuse", "isCorrect": false },
      { "label": "La fraternité uniquement", "isCorrect": false }
    ],
    "explanation": "Les libertés peuvent être encadrées par la loi.",
    "difficulty": "hard"
  },
  {
    "id": "dds034",
    "question": "Vous respectez les droits des autres usagers dans un lieu public. Quel devoir appliquez-vous ?",
    "type": "situational",
    "topic": "droits_devoirs",
    "choices": [
      { "label": "Le respect du vivre-ensemble", "isCorrect": true },
      { "label": "La neutralité", "isCorrect": false },
      { "label": "La laïcité", "isCorrect": false },
      { "label": "Le devoir fiscal", "isCorrect": false }
    ],
    "explanation": "Le vivre-ensemble repose sur le respect mutuel.",
    "difficulty": "medium"
  },
  {
    "id": "dds035",
    "question": "Vous exercez un métier réglementé et respectez ses règles. Quel devoir appliquez-vous ?",
    "type": "situational",
    "topic": "droits_devoirs",
    "choices": [
      { "label": "Le respect des règles professionnelles", "isCorrect": true },
      { "label": "La liberté totale", "isCorrect": false },
      { "label": "La neutralité religieuse", "isCorrect": false },
      { "label": "Le droit de grève", "isCorrect": false }
    ],
    "explanation": "Certaines professions impliquent des obligations spécifiques.",
    "difficulty": "medium"
  },

  {
    "id": "dds036",
    "question": "Vous respectez la liberté de la presse même lorsque les articles vous dérangent. Quel droit respectez-vous ?",
    "type": "situational",
    "topic": "droits_devoirs",
    "choices": [
      { "label": "La liberté de la presse", "isCorrect": true },
      { "label": "La neutralité", "isCorrect": false },
      { "label": "Le droit de vote", "isCorrect": false },
      { "label": "Le devoir fiscal", "isCorrect": false }
    ],
    "explanation": "La liberté de la presse est essentielle à la démocratie.",
    "difficulty": "medium"
  },
  {
    "id": "dds037",
    "question": "Vous respectez les droits des minorités même si vous appartenez à la majorité. Quel principe appliquez-vous ?",
    "type": "situational",
    "topic": "droits_devoirs",
    "choices": [
      { "label": "L’égalité des droits", "isCorrect": true },
      { "label": "La neutralité", "isCorrect": false },
      { "label": "La domination majoritaire", "isCorrect": false },
      { "label": "La liberté religieuse", "isCorrect": false }
    ],
    "explanation": "L’égalité protège tous les citoyens.",
    "difficulty": "medium"
  },
  {
    "id": "dds038",
    "question": "Vous acceptez de remplir vos obligations administratives (recensement, documents). Quel devoir appliquez-vous ?",
    "type": "situational",
    "topic": "droits_devoirs",
    "choices": [
      { "label": "Le respect des obligations civiques", "isCorrect": true },
      { "label": "La neutralité", "isCorrect": false },
      { "label": "La liberté religieuse", "isCorrect": false },
      { "label": "Le droit de grève", "isCorrect": false }
    ],
    "explanation": "Les démarches administratives font partie des devoirs.",
    "difficulty": "medium"
  },
  {
    "id": "dds039",
    "question": "Vous acceptez de débattre sans insulter ni menacer. Quel devoir respectez-vous ?",
    "type": "situational",
    "topic": "droits_devoirs",
    "choices": [
      { "label": "Le respect du débat démocratique", "isCorrect": true },
      { "label": "La neutralité", "isCorrect": false },
      { "label": "La laïcité", "isCorrect": false },
      { "label": "Le devoir fiscal", "isCorrect": false }
    ],
    "explanation": "Le débat pacifique est au cœur de la démocratie.",
    "difficulty": "medium"
  },
  {
    "id": "dds040",
    "question": "Vous respectez les droits et les devoirs de tous dans votre vie quotidienne. Quel comportement adoptez-vous ?",
    "type": "situational",
    "topic": "droits_devoirs",
    "choices": [
      { "label": "Un comportement citoyen conforme aux valeurs républicaines", "isCorrect": true },
      { "label": "Une soumission administrative", "isCorrect": false },
      { "label": "Une neutralité politique", "isCorrect": false },
      { "label": "Un simple choix personnel", "isCorrect": false }
    ],
    "explanation": "Être citoyen implique droits et devoirs.",
    "difficulty": "medium"
  },
  {
    "id": "dds041",
    "question": "La France est en guerre. Est-ce que je suis obligé de défendre le pays ?",
    "type": "situational",
    "topic": "droits_devoirs",
    "choices": [
      { "label": "En cas de mobilisation générale, les citoyens peuvent être appelés à défendre le pays", "isCorrect": true },
      { "label": "Non, le service militaire est aboli", "isCorrect": false },
      { "label": "Non, seuls les militaires professionnels combattent", "isCorrect": false },
      { "label": "Oui, mais uniquement les hommes", "isCorrect": false }
    ],
    "explanation": "La défense de la nation peut impliquer la mobilisation des citoyens en cas de guerre.",
    "difficulty": "hard"
  },
  {
    "id": "dds042",
    "question": "Est-ce que le maire peut refuser de marier un couple homosexuel ?",
    "type": "situational",
    "topic": "droits_devoirs",
    "choices": [
      { "label": "Non, c'est une obligation légale depuis 2013", "isCorrect": true },
      { "label": "Oui, pour des raisons de conscience", "isCorrect": false },
      { "label": "Oui, si la commune est contre", "isCorrect": false },
      { "label": "Oui, s'il délègue à un adjoint", "isCorrect": false }
    ],
    "explanation": "Le mariage pour tous est un droit, le maire ne peut refuser de célébrer un mariage légal.",
    "difficulty": "hard"
  },
  {
    "id": "dds043",
    "question": "Tu es appelé à voter mais tu ne t'intéresses pas à la politique. Est-ce que tu dois voter ?",
    "type": "situational",
    "topic": "droits_devoirs",
    "choices": [
      { "label": "Le vote n'est pas obligatoire mais c'est un devoir civique", "isCorrect": true },
      { "label": "Oui, le vote est obligatoire en France", "isCorrect": false },
      { "label": "Non, et il n'y a aucune conséquence", "isCorrect": false },
      { "label": "Oui, sous peine d'amende", "isCorrect": false }
    ],
    "explanation": "Le vote est un droit et un devoir civique, mais pas une obligation légale en France.",
    "difficulty": "medium"
  },
  {
    "id": "dds044",
    "question": "Un professeur sanctionne un élève pour son comportement. Quels droits l'élève conserve-t-il malgré la sanction ?",
    "type": "situational",
    "topic": "droits_devoirs",
    "choices": [
      { "label": "Le droit à la défense et le droit de contester la sanction", "isCorrect": true },
      { "label": "Aucun, la sanction est définitive", "isCorrect": false },
      { "label": "Le droit de ne plus venir en cours", "isCorrect": false },
      { "label": "Le droit de changer d'établissement automatiquement", "isCorrect": false }
    ],
    "explanation": "Même sanctionné, l'élève conserve ses droits fondamentaux dont celui de contester.",
    "difficulty": "medium"
  },
  {
    "id": "dds045",
    "question": "Un citoyen refuse de payer ses impôts en affirmant que c'est son droit. A-t-il le droit ?",
    "type": "situational",
    "topic": "droits_devoirs",
    "choices": [
      { "label": "Non, le paiement des impôts est une obligation légale", "isCorrect": true },
      { "label": "Oui, si ses revenus sont faibles", "isCorrect": false },
      { "label": "Oui, c'est une liberté individuelle", "isCorrect": false },
      { "label": "Oui, s'il conteste l'utilisation de l'argent public", "isCorrect": false }
    ],
    "explanation": "Le paiement des impôts est un devoir citoyen inscrit dans la loi.",
    "difficulty": "medium"
  },
  {
    "id": "dds046",
    "question": "Un élève refuse de faire son travail scolaire en disant qu'il est libre. A-t-il le droit ?",
    "type": "situational",
    "topic": "droits_devoirs",
    "choices": [
      { "label": "Non, l'instruction est obligatoire et implique des devoirs", "isCorrect": true },
      { "label": "Oui, la liberté est un droit fondamental", "isCorrect": false },
      { "label": "Oui, s'il assume les conséquences", "isCorrect": false },
      { "label": "Oui, après 16 ans", "isCorrect": false }
    ],
    "explanation": "L'instruction obligatoire implique le respect des règles scolaires et du travail demandé.",
    "difficulty": "medium"
  },
  {
    "id": "dds047",
    "question": "Tu es témoin de harcèlement au travail. Quels sont tes devoirs en tant que témoin ?",
    "type": "situational",
    "topic": "droits_devoirs",
    "choices": [
      { "label": "Signaler les faits et témoigner si nécessaire", "isCorrect": true },
      { "label": "Ne rien faire pour ne pas avoir de problèmes", "isCorrect": false },
      { "label": "Régler le problème soi-même avec le harceleur", "isCorrect": false },
      { "label": "Attendre que la victime porte plainte", "isCorrect": false }
    ],
    "explanation": "Le témoin a un devoir moral et peut être protégé légalement s'il signale les faits.",
    "difficulty": "hard"
  },
  {
    "id": "dds048",
    "question": "Tu trouves un objet perdu dans la rue. Est-ce que tu peux le garder ?",
    "type": "situational",
    "topic": "droits_devoirs",
    "choices": [
      { "label": "Non, il faut le déposer à la mairie ou au commissariat", "isCorrect": true },
      { "label": "Oui, celui qui trouve garde", "isCorrect": false },
      { "label": "Oui, si personne ne le réclame dans l'heure", "isCorrect": false },
      { "label": "Oui, si l'objet a peu de valeur", "isCorrect": false }
    ],
    "explanation": "Garder un objet trouvé sans le déclarer peut constituer un abus de confiance.",
    "difficulty": "medium"
  },
  {
    "id": "dds049",
    "question": "Un journaliste publie des informations privées sur une personne connue. Quels droits sont en conflit ?",
    "type": "situational",
    "topic": "droits_devoirs",
    "choices": [
      { "label": "La liberté de la presse et le droit au respect de la vie privée", "isCorrect": true },
      { "label": "La liberté d'expression et le droit de vote", "isCorrect": false },
      { "label": "Le droit à l'information et le droit de grève", "isCorrect": false },
      { "label": "La liberté de conscience et le droit syndical", "isCorrect": false }
    ],
    "explanation": "La presse doit respecter la vie privée, même pour les personnalités publiques.",
    "difficulty": "hard"
  },
  {
    "id": "dds050",
    "question": "Vous refusez de respecter une loi car vous n'êtes pas d'accord avec elle. Est-ce autorisé en France ?",
    "type": "situational",
    "topic": "droits_devoirs",
    "choices": [
      { "label": "Non, la loi s'applique à tous, la contestation passe par des voies légales", "isCorrect": true },
      { "label": "Oui, c'est la liberté d'opinion", "isCorrect": false },
      { "label": "Oui, si la majorité est d'accord", "isCorrect": false },
      { "label": "Oui, pour des raisons de conscience", "isCorrect": false }
    ],
    "explanation": "Dans un État de droit, nul ne peut choisir les lois qu'il respecte.",
    "difficulty": "medium"
  },
  {
    "id": "dds051",
    "question": "Une personne tient des propos racistes dans un lieu public. Que risque-t-elle ?",
    "type": "situational",
    "topic": "droits_devoirs",
    "choices": [
      { "label": "Des poursuites pénales pour injure ou incitation à la haine raciale", "isCorrect": true },
      { "label": "Rien, c'est la liberté d'expression", "isCorrect": false },
      { "label": "Un simple rappel à l'ordre", "isCorrect": false },
      { "label": "Une amende uniquement si quelqu'un porte plainte", "isCorrect": false }
    ],
    "explanation": "Les propos racistes sont punis par la loi, même sans plainte dans certains cas.",
    "difficulty": "hard"
  },
  {
    "id": "dds052",
    "question": "Vous êtes appelé à participer à la Journée Défense et Citoyenneté. Quel est le sens de cet engagement ?",
    "type": "situational",
    "topic": "droits_devoirs",
    "choices": [
      { "label": "Sensibiliser les jeunes à leurs devoirs envers la nation", "isCorrect": true },
      { "label": "Recruter de force pour l'armée", "isCorrect": false },
      { "label": "Remplacer le service militaire obligatoire", "isCorrect": false },
      { "label": "Obtenir le droit de vote", "isCorrect": false }
    ],
    "explanation": "La JDC informe sur les droits et devoirs du citoyen et la défense nationale.",
    "difficulty": "medium"
  },
  {
    "id": "dds053",
    "question": "Un citoyen détruit un bien public lors d'une manifestation. Quels devoirs n'ont pas été respectés ?",
    "type": "situational",
    "topic": "droits_devoirs",
    "choices": [
      { "label": "Le respect des biens publics et de la loi", "isCorrect": true },
      { "label": "Le droit de manifester uniquement", "isCorrect": false },
      { "label": "La liberté d'expression", "isCorrect": false },
      { "label": "Le devoir de réserve", "isCorrect": false }
    ],
    "explanation": "Manifester est un droit, mais la destruction de biens publics est un délit.",
    "difficulty": "medium"
  },
  {
    "id": "dds054",
    "question": "Mon enfant n'aime pas les mathématiques. Est-ce qu'il peut ne pas suivre ces cours à l'école ?",
    "type": "situational",
    "topic": "droits_devoirs",
    "choices": [
      { "label": "Non, les programmes scolaires sont obligatoires pour tous", "isCorrect": true },
      { "label": "Oui, si les parents l'autorisent", "isCorrect": false },
      { "label": "Oui, au nom de la liberté éducative", "isCorrect": false },
      { "label": "Oui, s'il compense par une autre matière", "isCorrect": false }
    ],
    "explanation": "L'instruction obligatoire impose de suivre l'ensemble du programme scolaire.",
    "difficulty": "medium"
  },

  {
    "id": "dds055",
    "question": "Un citoyen est convoqué comme assesseur dans un bureau de vote. Peut-il refuser ?",
    "type": "situational",
    "topic": "droits_devoirs",
    "choices": [
      { "label": "L'absence non justifiée peut être sanctionnée", "isCorrect": true },
      { "label": "Oui, c'est du bénévolat", "isCorrect": false },
      { "label": "Non, mais il n'y a aucune sanction possible", "isCorrect": false },
      { "label": "Oui, si un autre volontaire le remplace", "isCorrect": false }
    ],
    "explanation": "Être assesseur est une fonction civique dont le refus injustifié peut être sanctionné.",
    "difficulty": "hard"
  },
  {
    "id": "dds056",
    "question": "Un Français vivant à l'étranger depuis 20 ans doit-il faire la Journée Défense et Citoyenneté ?",
    "type": "situational",
    "topic": "droits_devoirs",
    "choices": [
      { "label": "Oui, c'est obligatoire pour tous les Français", "isCorrect": true },
      { "label": "Non, il est dispensé car il vit à l'étranger", "isCorrect": false },
      { "label": "Oui, mais uniquement s'il revient en France", "isCorrect": false },
      { "label": "Non, après 10 ans à l'étranger c'est facultatif", "isCorrect": false }
    ],
    "explanation": "La JDC est obligatoire pour tous les citoyens français, quel que soit leur lieu de résidence.",
    "difficulty": "hard"
  },
  {
    "id": "dds057",
    "question": "Un citoyen refuse de se soumettre à un test d'alcoolémie lors d'un contrôle routier. Que risque-t-il ?",
    "type": "situational",
    "topic": "droits_devoirs",
    "choices": [
      { "label": "Des sanctions plus lourdes que celles prévues pour l'alcoolémie elle-même", "isCorrect": true },
      { "label": "Rien, c'est son droit de refuser", "isCorrect": false },
      { "label": "Une simple amende forfaitaire", "isCorrect": false },
      { "label": "Un avertissement verbal uniquement", "isCorrect": false }
    ],
    "explanation": "Le refus de se soumettre au dépistage est un délit plus sévèrement puni que l'alcoolémie positive.",
    "difficulty": "hard"
  },
  {
    "id": "dds058",
    "question": "Un témoin d'un crime refuse de témoigner par peur de représailles. A-t-il le droit ?",
    "type": "situational",
    "topic": "droits_devoirs",
    "choices": [
      { "label": "Non, mais des dispositifs de protection des témoins existent", "isCorrect": true },
      { "label": "Oui, la peur est un motif légitime", "isCorrect": false },
      { "label": "Non, et il sera poursuivi pour complicité", "isCorrect": false },
      { "label": "Oui, si le crime ne le concerne pas directement", "isCorrect": false }
    ],
    "explanation": "Le témoignage est un devoir, mais la loi prévoit des protections pour les témoins menacés.",
    "difficulty": "hard"
  },
  {
    "id": "dds059",
    "question": "Un citoyen trouve une erreur en sa faveur sur sa feuille d'impôts. Doit-il la signaler ?",
    "type": "situational",
    "topic": "droits_devoirs",
    "choices": [
      { "label": "Oui, la déclaration sincère est une obligation", "isCorrect": true },
      { "label": "Non, c'est l'erreur de l'administration", "isCorrect": false },
      { "label": "Oui, mais seulement si l'erreur dépasse 500 euros", "isCorrect": false },
      { "label": "Non, seules les erreurs en sa défaveur se signalent", "isCorrect": false }
    ],
    "explanation": "La sincérité fiscale impose de signaler toute erreur, même favorable au contribuable.",
    "difficulty": "hard"
  },
  {
    "id": "dds060",
    "question": "Un accusé refuse de répondre aux questions du juge. A-t-il le droit ?",
    "type": "situational",
    "topic": "droits_devoirs",
    "choices": [
      { "label": "Oui, le droit au silence est garanti", "isCorrect": true },
      { "label": "Non, il doit répondre à toutes les questions", "isCorrect": false },
      { "label": "Oui, mais cela sera retenu contre lui", "isCorrect": false },
      { "label": "Non, sauf s'il a un avocat", "isCorrect": false }
    ],
    "explanation": "Le droit au silence est un droit fondamental qui ne peut être utilisé contre l'accusé.",
    "difficulty": "hard"
  },
  {
    "id": "dds061",
    "question": "Un citoyen est placé en garde à vue. Peut-il refuser de donner ses empreintes ?",
    "type": "situational",
    "topic": "droits_devoirs",
    "choices": [
      { "label": "Non, c'est une obligation légale en garde à vue", "isCorrect": true },
      { "label": "Oui, c'est une atteinte à la vie privée", "isCorrect": false },
      { "label": "Oui, s'il n'est pas encore inculpé", "isCorrect": false },
      { "label": "Non, mais uniquement pour les crimes", "isCorrect": false }
    ],
    "explanation": "Le relevé d'empreintes est obligatoire en garde à vue, le refus est une infraction.",
    "difficulty": "hard"
  },
  {
    "id": "dds062",
    "question": "Une victime d'agression refuse de porter plainte. La police peut-elle poursuivre ?",
    "type": "situational",
    "topic": "droits_devoirs",
    "choices": [
      { "label": "Oui, pour certaines infractions le ministère public peut se saisir d'office", "isCorrect": true },
      { "label": "Non, sans plainte il n'y a pas de poursuite", "isCorrect": false },
      { "label": "Oui, mais seulement pour les crimes", "isCorrect": false },
      { "label": "Non, la victime a le dernier mot", "isCorrect": false }
    ],
    "explanation": "Le ministère public peut engager des poursuites d'office pour les infractions graves.",
    "difficulty": "hard"
  },
  {
    "id": "dds063",
    "question": "Un citoyen est acquitté mais sa photo a circulé dans les médias. A-t-il un recours ?",
    "type": "situational",
    "topic": "droits_devoirs",
    "choices": [
      { "label": "Oui, pour atteinte à la présomption d'innocence", "isCorrect": true },
      { "label": "Non, les médias sont libres d'informer", "isCorrect": false },
      { "label": "Oui, mais seulement si les photos sont récentes", "isCorrect": false },
      { "label": "Non, l'acquittement suffit à réparer le préjudice", "isCorrect": false }
    ],
    "explanation": "La présomption d'innocence est protégée et sa violation ouvre droit à réparation.",
    "difficulty": "hard"
  },
  {
    "id": "dds064",
    "question": "Un juge est ami avec une des parties au procès. Que doit-il faire ?",
    "type": "situational",
    "topic": "droits_devoirs",
    "choices": [
      { "label": "Se déporter et ne pas juger l'affaire", "isCorrect": true },
      { "label": "Juger en toute impartialité malgré tout", "isCorrect": false },
      { "label": "Demander l'avis des autres parties", "isCorrect": false },
      { "label": "Signaler le lien mais continuer à juger", "isCorrect": false }
    ],
    "explanation": "L'impartialité du juge impose qu'il se déporte en cas de lien personnel avec une partie.",
    "difficulty": "hard"
  },
  {
    "id": "dds065",
    "question": "Un salarié refuse de travailler car il estime sa sécurité en danger. A-t-il le droit ?",
    "type": "situational",
    "topic": "droits_devoirs",
    "choices": [
      { "label": "Oui, c'est le droit de retrait si le danger est réel et imminent", "isCorrect": true },
      { "label": "Non, il doit travailler et signaler ensuite", "isCorrect": false },
      { "label": "Oui, pour n'importe quelle inquiétude", "isCorrect": false },
      { "label": "Non, sauf autorisation de l'employeur", "isCorrect": false }
    ],
    "explanation": "Le droit de retrait permet au salarié de se protéger d'un danger grave et imminent.",
    "difficulty": "hard"
  },
  {
    "id": "dds066",
    "question": "Un employeur peut-il interdire les discussions politiques au travail ?",
    "type": "situational",
    "topic": "droits_devoirs",
    "choices": [
      { "label": "Oui, pour préserver la neutralité et le bon fonctionnement", "isCorrect": true },
      { "label": "Non, la liberté d'expression est absolue", "isCorrect": false },
      { "label": "Oui, mais uniquement dans la fonction publique", "isCorrect": false },
      { "label": "Non, sauf pendant les heures de travail effectif", "isCorrect": false }
    ],
    "explanation": "L'employeur peut limiter les discussions politiques pour maintenir un climat de travail serein.",
    "difficulty": "hard"
  },
  {
    "id": "dds067",
    "question": "Un salarié refuse une mutation prévue dans son contrat. Que risque-t-il ?",
    "type": "situational",
    "topic": "droits_devoirs",
    "choices": [
      { "label": "Un licenciement pour faute si la clause de mobilité est valide", "isCorrect": true },
      { "label": "Rien, la mobilité ne peut être imposée", "isCorrect": false },
      { "label": "Une retenue sur salaire uniquement", "isCorrect": false },
      { "label": "Un avertissement sans autre conséquence", "isCorrect": false }
    ],
    "explanation": "Une clause de mobilité valide dans le contrat s'impose au salarié.",
    "difficulty": "hard"
  },
  {
    "id": "dds068",
    "question": "Un employeur peut-il consulter les emails personnels d'un salarié sur l'ordinateur professionnel ?",
    "type": "situational",
    "topic": "droits_devoirs",
    "choices": [
      { "label": "Non, si les messages sont identifiés comme personnels", "isCorrect": true },
      { "label": "Oui, l'ordinateur appartient à l'entreprise", "isCorrect": false },
      { "label": "Oui, pendant les heures de travail", "isCorrect": false },
      { "label": "Non, mais il peut les supprimer", "isCorrect": false }
    ],
    "explanation": "Les emails identifiés comme personnels sont protégés par le secret des correspondances.",
    "difficulty": "hard"
  },
  {
    "id": "dds069",
    "question": "Un stagiaire travaille 10 heures par jour sans pause. Est-ce légal ?",
    "type": "situational",
    "topic": "droits_devoirs",
    "choices": [
      { "label": "Non, le Code du travail s'applique aussi aux stagiaires", "isCorrect": true },
      { "label": "Oui, les stagiaires ne sont pas des salariés", "isCorrect": false },
      { "label": "Oui, si la convention de stage le prévoit", "isCorrect": false },
      { "label": "Non, mais seulement pour les mineurs", "isCorrect": false }
    ],
    "explanation": "Les stagiaires bénéficient des protections du Code du travail sur la durée et les pauses.",
    "difficulty": "hard"
  },
  {
    "id": "dds070",
    "question": "Un mineur de 16 ans veut quitter le domicile familial. A-t-il le droit ?",
    "type": "situational",
    "topic": "droits_devoirs",
    "choices": [
      { "label": "Non sans l'accord des parents ou une décision de justice", "isCorrect": true },
      { "label": "Oui, à partir de 16 ans c'est autorisé", "isCorrect": false },
      { "label": "Oui, s'il a un travail", "isCorrect": false },
      { "label": "Non, jamais avant 18 ans", "isCorrect": false }
    ],
    "explanation": "L'autorité parentale s'exerce jusqu'à 18 ans, sauf émancipation ou décision judiciaire.",
    "difficulty": "hard"
  },
  {
    "id": "dds071",
    "question": "Des parents refusent une transfusion sanguine pour leur enfant pour raisons religieuses. Que se passe-t-il ?",
    "type": "situational",
    "topic": "droits_devoirs",
    "choices": [
      { "label": "Le médecin peut passer outre si la vie de l'enfant est en danger", "isCorrect": true },
      { "label": "Les parents ont le dernier mot", "isCorrect": false },
      { "label": "Le médecin doit respecter le refus", "isCorrect": false },
      { "label": "Il faut attendre une décision de justice", "isCorrect": false }
    ],
    "explanation": "L'intérêt supérieur de l'enfant permet au médecin d'agir en urgence vitale.",
    "difficulty": "hard"
  },
  {
    "id": "dds072",
    "question": "Un enfant adopté veut connaître ses origines biologiques. A-t-il le droit ?",
    "type": "situational",
    "topic": "droits_devoirs",
    "choices": [
      { "label": "Oui, sous certaines conditions depuis la loi de 2022", "isCorrect": true },
      { "label": "Non, l'adoption efface les origines", "isCorrect": false },
      { "label": "Oui, sans aucune restriction", "isCorrect": false },
      { "label": "Non, sauf accord des parents biologiques", "isCorrect": false }
    ],
    "explanation": "La loi facilite désormais l'accès aux origines pour les personnes adoptées.",
    "difficulty": "hard"
  },
  {
    "id": "dds073",
    "question": "Un parent empêche l'autre parent de voir son enfant malgré un jugement. Que risque-t-il ?",
    "type": "situational",
    "topic": "droits_devoirs",
    "choices": [
      { "label": "Des poursuites pour non-représentation d'enfant", "isCorrect": true },
      { "label": "Rien, c'est un conflit familial privé", "isCorrect": false },
      { "label": "Une simple médiation obligatoire", "isCorrect": false },
      { "label": "Une amende civile uniquement", "isCorrect": false }
    ],
    "explanation": "La non-représentation d'enfant est un délit pénal passible d'emprisonnement.",
    "difficulty": "hard"
  },
  {
    "id": "dds074",
    "question": "Un mineur de 15 ans peut-il travailler pendant les vacances scolaires ?",
    "type": "situational",
    "topic": "droits_devoirs",
    "choices": [
      { "label": "Oui, avec des conditions strictes et l'autorisation parentale", "isCorrect": true },
      { "label": "Non, le travail est interdit avant 16 ans", "isCorrect": false },
      { "label": "Oui, sans aucune restriction", "isCorrect": false },
      { "label": "Non, sauf pour les métiers du spectacle", "isCorrect": false }
    ],
    "explanation": "Le travail des mineurs de 14-16 ans est possible pendant les vacances sous conditions strictes.",
    "difficulty": "hard"
  },
  {
    "id": "dds075",
    "question": "Un usager insulte un agent public qui refuse sa demande. Que risque-t-il ?",
    "type": "situational",
    "topic": "droits_devoirs",
    "choices": [
      { "label": "Des poursuites pour outrage à personne dépositaire de l'autorité publique", "isCorrect": true },
      { "label": "Rien, c'est la liberté d'expression", "isCorrect": false },
      { "label": "Un simple refus de service", "isCorrect": false },
      { "label": "Une amende administrative", "isCorrect": false }
    ],
    "explanation": "L'outrage à agent public est un délit pénal puni d'amende et d'emprisonnement.",
    "difficulty": "hard"
  },
  {
    "id": "dds076",
    "question": "Une administration ne répond pas à une demande dans les délais. Que peut faire le citoyen ?",
    "type": "situational",
    "topic": "droits_devoirs",
    "choices": [
      { "label": "Considérer que le silence vaut acceptation ou rejet selon les cas", "isCorrect": true },
      { "label": "Rien, il faut attendre la réponse", "isCorrect": false },
      { "label": "Porter plainte immédiatement", "isCorrect": false },
      { "label": "Renouveler sa demande automatiquement", "isCorrect": false }
    ],
    "explanation": "Le silence de l'administration a une valeur juridique qui varie selon les procédures.",
    "difficulty": "hard"
  },
  {
    "id": "dds077",
    "question": "Un citoyen conteste un PV de stationnement qu'il juge injuste. Quelle est la procédure ?",
    "type": "situational",
    "topic": "droits_devoirs",
    "choices": [
      { "label": "Contester d'abord auprès de l'officier du ministère public", "isCorrect": true },
      { "label": "Payer puis demander un remboursement", "isCorrect": false },
      { "label": "Saisir directement le tribunal", "isCorrect": false },
      { "label": "Écrire au maire de la commune", "isCorrect": false }
    ],
    "explanation": "La contestation d'un PV suit une procédure spécifique avec recours préalable obligatoire.",
    "difficulty": "hard"
  },
  {
    "id": "dds078",
    "question": "Un fonctionnaire reçoit un ordre manifestement illégal. Doit-il obéir ?",
    "type": "situational",
    "topic": "droits_devoirs",
    "choices": [
      { "label": "Non, il a le devoir de désobéir aux ordres manifestement illégaux", "isCorrect": true },
      { "label": "Oui, l'obéissance hiérarchique prime", "isCorrect": false },
      { "label": "Oui, mais il peut signaler ensuite", "isCorrect": false },
      { "label": "Non, sauf ordre écrit de son supérieur", "isCorrect": false }
    ],
    "explanation": "Le fonctionnaire doit refuser d'exécuter un ordre manifestement illégal.",
    "difficulty": "hard"
  },
  {
    "id": "dds079",
    "question": "Un citoyen demande l'accès à un document administratif le concernant. L'administration peut-elle refuser ?",
    "type": "situational",
    "topic": "droits_devoirs",
    "choices": [
      { "label": "En principe non, sauf exceptions prévues par la loi", "isCorrect": true },
      { "label": "Oui, les documents administratifs sont confidentiels", "isCorrect": false },
      { "label": "Non, jamais aucune exception", "isCorrect": false },
      { "label": "Oui, si le document est ancien", "isCorrect": false }
    ],
    "explanation": "Le droit d'accès aux documents administratifs est garanti avec des exceptions limitées.",
    "difficulty": "hard"
  },
  {
    "id": "dds080",
    "question": "Un citoyen trouve une arme dans la rue. Que doit-il faire ?",
    "type": "situational",
    "topic": "droits_devoirs",
    "choices": [
      { "label": "Prévenir immédiatement la police sans toucher l'arme", "isCorrect": true },
      { "label": "Rapporter l'arme au commissariat", "isCorrect": false },
      { "label": "La mettre en sécurité chez lui", "isCorrect": false },
      { "label": "La laisser sur place sans rien faire", "isCorrect": false }
    ],
    "explanation": "Manipuler une arme trouvée peut compromettre une enquête et constituer une infraction.",
    "difficulty": "hard"
  },
  {
    "id": "dds081",
    "question": "Un voisin menace de se suicider. Quels sont vos devoirs ?",
    "type": "situational",
    "topic": "droits_devoirs",
    "choices": [
      { "label": "Alerter les secours, le devoir d'assistance s'applique", "isCorrect": true },
      { "label": "Respecter sa vie privée et ne rien faire", "isCorrect": false },
      { "label": "Essayer de le raisonner soi-même", "isCorrect": false },
      { "label": "Prévenir sa famille uniquement", "isCorrect": false }
    ],
    "explanation": "Le devoir d'assistance à personne en danger impose d'alerter les secours.",
    "difficulty": "hard"
  },
  {
    "id": "dds082",
    "question": "Un citoyen est témoin d'un vol mais le voleur est un ami. Doit-il témoigner ?",
    "type": "situational",
    "topic": "droits_devoirs",
    "choices": [
      { "label": "Oui, l'amitié ne dispense pas du devoir de témoigner", "isCorrect": true },
      { "label": "Non, on ne témoigne pas contre un ami", "isCorrect": false },
      { "label": "Oui, mais il peut mentir pour le protéger", "isCorrect": false },
      { "label": "Non, sauf si le vol est grave", "isCorrect": false }
    ],
    "explanation": "Le devoir de témoigner s'impose à tous, les liens personnels ne sont pas une excuse.",
    "difficulty": "hard"
  },
  {
    "id": "dds083",
    "question": "Un patient refuse un traitement vital en pleine conscience. Le médecin peut-il le forcer ?",
    "type": "situational",
    "topic": "droits_devoirs",
    "choices": [
      { "label": "Non, le consentement du patient est obligatoire sauf urgence vitale", "isCorrect": true },
      { "label": "Oui, le médecin doit sauver la vie", "isCorrect": false },
      { "label": "Non, jamais en aucune circonstance", "isCorrect": false },
      { "label": "Oui, avec l'accord de la famille", "isCorrect": false }
    ],
    "explanation": "Le patient conscient a le droit de refuser un traitement, même vital.",
    "difficulty": "hard"
  },
  {
    "id": "dds084",
    "question": "Un citoyen découvre que son voisin fraude les aides sociales. A-t-il l'obligation de dénoncer ?",
    "type": "situational",
    "topic": "droits_devoirs",
    "choices": [
      { "label": "Non, il n'y a pas d'obligation légale mais il peut signaler", "isCorrect": true },
      { "label": "Oui, c'est une obligation civique", "isCorrect": false },
      { "label": "Non, et le signalement est interdit", "isCorrect": false },
      { "label": "Oui, sous peine d'être complice", "isCorrect": false }
    ],
    "explanation": "Il n'existe pas d'obligation générale de dénonciation, mais le signalement est possible.",
    "difficulty": "hard"
  }
]